pyspcalt/__init__.py
pyspcalt/pyspcalt.py
pyspcalt/results.py
pyspcalt/rules.py
pyspcalt/ccharts/__init__.py
pyspcalt/ccharts/c.py
pyspcalt/ccharts/ccharts.py
pyspcalt/ccharts/cusum.py
pyspcalt/ccharts/ewma.py
pyspcalt/ccharts/hotelling.py
pyspcalt/ccharts/imrmr.py
pyspcalt/ccharts/imrr.py
pyspcalt/ccharts/imrstd.py
pyspcalt/ccharts/imrx.py
pyspcalt/ccharts/mr.py
pyspcalt/ccharts/np.py
pyspcalt/ccharts/p.py
pyspcalt/ccharts/tables.py
pyspcalt/ccharts/u.py
pyspcalt/ccharts/xbar_rbar.py
pyspcalt/ccharts/xbar_sbar.py
pyspcalt/sampledata/PaintMaterial.csv
pyspcalt/sampledata/Viscosidade.csv
pyspcalt/sampledata/__init__.py
pyspcalt/sampledata/canjuice.csv
pyspcalt/sampledata/chemical.csv
pyspcalt/sampledata/circuits.csv
pyspcalt/sampledata/dados.csv
pyspcalt/sampledata/diameter.csv
pyspcalt/sampledata/experiment.csv
pyspcalt/sampledata/grams.csv
pyspcalt/sampledata/hotelling.csv
pyspcalt/sampledata/inspection.csv
pyspcalt/sampledata/newproduct.csv
pyspcalt/sampledata/parts.csv
pyspcalt/sampledata/pistonrings.csv
pyspcalt/sampledata/sandbox.csv
pyspcalt/sampledata/sizes.csv
pyspcalt/sampledata/thickness.csv
pyspcalt/sampledata/waitingTime.csv
tests/__init__.py
tests/pyspc_test.py
pyspcalt-1.0.10.dist-info/LICENSE
pyspcalt-1.0.10.dist-info/METADATA
pyspcalt-1.0.10.dist-info/WHEEL
pyspcalt-1.0.10.dist-info/top_level.txt
pyspcalt-1.0.10.dist-info/RECORD
